georise/__init__.py
georise/constants.py
georise/glview.py
georise/overlay.py
georise/provider.py
georise/raster.py
georise/scene.py
georise/transform.py
georise/util.py
tests/__init__.py
tests/test_provider.py
tests/test_raster.py
tests/test_transform.py
georise-0.0.1.dist-info/METADATA
georise-0.0.1.dist-info/WHEEL
georise-0.0.1.dist-info/top_level.txt
georise-0.0.1.dist-info/RECORD
